soundswallower/__init__.py
soundswallower/_soundswallower.cp310-win_amd64.pyd
soundswallower/_soundswallower.pyi
soundswallower/cli.py
soundswallower/model/en-us/dict.txt
soundswallower/model/en-us/feat_params.json
soundswallower/model/en-us/mdef
soundswallower/model/en-us/mdef.txt
soundswallower/model/en-us/means
soundswallower/model/en-us/noisedict.txt
soundswallower/model/en-us/phoneset.json
soundswallower/model/en-us/README.txt
soundswallower/model/en-us/sendump
soundswallower/model/en-us/transition_matrices
soundswallower/model/en-us/variances
soundswallower/model/fr-fr/dict.txt
soundswallower/model/fr-fr/feat_params.json
soundswallower/model/fr-fr/LICENSE.txt
soundswallower/model/fr-fr/mdef
soundswallower/model/fr-fr/mdef.txt
soundswallower/model/fr-fr/means
soundswallower/model/fr-fr/noisedict.txt
soundswallower/model/fr-fr/phoneset.json
soundswallower/model/fr-fr/README.txt
soundswallower/model/fr-fr/sendump
soundswallower/model/fr-fr/transition_matrices
soundswallower/model/fr-fr/variances
soundswallower/py.typed
soundswallower-0.6.5.dist-info/METADATA
soundswallower-0.6.5.dist-info/WHEEL
soundswallower-0.6.5.dist-info/entry_points.txt
soundswallower-0.6.5.dist-info/licenses/LICENSE
soundswallower-0.6.5.dist-info/RECORD
