Metadata-Version: 2.1
Name: soundswallower
Version: 0.6.5
Summary: An even smaller speech recognizer
Keywords: asr,speech
Author-Email: David Huggins-Daines <dhd@ecolingui.ca>
Classifier: Development Status :: 3 - Alpha
Classifier: Programming Language :: C
Classifier: Programming Language :: Cython
Classifier: Programming Language :: Python :: 3
Classifier: Programming Language :: Python :: 3.8
Classifier: Programming Language :: Python :: 3.9
Classifier: Programming Language :: Python :: 3.10
Classifier: Programming Language :: Python :: 3.11
Classifier: Programming Language :: Python :: 3.12
Classifier: Programming Language :: Python :: 3.13
Classifier: License :: OSI Approved :: BSD License
Classifier: Operating System :: OS Independent
Classifier: Topic :: Multimedia :: Sound/Audio :: Speech
Project-URL: Homepage, https://github.com/ReadAlongs/SoundSwallower
Project-URL: Documentation, https://soundswallower.readthedocs.io/
Project-URL: Repository, https://github.com/ReadAlongs/SoundSwallower.git
Project-URL: Issues, https://github.com/ReadAlongs/SoundSwallower/issues
